{
  "intents": [
    {
      "tag": "greeting",
      "patterns": [
        "Xin chào",
        "Chào bạn",
        "Hi",
        "Hello",
        "Chào bot",
        "Có ai ở đó không"
      ],
      "responses": [
        "Xin chào! Tôi là trợ lý ảo thư viện. Bạn cần giúp gì?",
        "Chào bạn, tôi có thể hỗ trợ gì cho bạn hôm nay?"
      ]
    },
    {
      "tag": "faq",
      "patterns": [
        "Thư viện mở cửa lúc mấy giờ?",
        "Giờ làm việc của thư viện",
        "Làm sao để mượn sách?",
        "Quy trình trả sách",
        "Liên hệ thư viện thế nào?",
        "Số điện thoại thư viện",
        "Email của thư viện",
        "Có wifi không?",
        "Mật khẩu wifi là gì",
        "Quy định mượn sách",
        "Tôi bị mất thẻ thư viện"
      ],
      "responses": [
        "Để tôi tra cứu thông tin quy định cho bạn..."
      ]
    },
    {
      "tag": "books",
      "patterns": [
        "Tìm sách lập trình",
        "Có sách Python không?",
        "Sách về kinh tế",
        "Kiểm tra sách này còn không",
        "Tác giả Nguyễn Nhật Ánh",
        "Sách giáo trình Toán cao cấp",
        "Tôi muốn tìm tài liệu về Marketing",
        "Tra cứu sách",
        "Danh sách sách mới"
      ],
      "responses": [
        "Đợi chút, tôi sẽ tìm trong kho sách..."
      ]
    },
    {
      "tag": "majors",
      "patterns": [
        "Ngành Công nghệ thông tin học gì?",
        "Mã ngành Quản trị kinh doanh",
        "Thông tin về ngành Kế toán",
        "Chương trình đào tạo ngành Ngôn ngữ Anh",
        "Ngành này ra trường làm gì?",
        "Giới thiệu về khoa CNTT",
        "Các ngành đào tạo của trường"
      ],
      "responses": [
        "Để tôi lấy thông tin về ngành học này..."
      ]
    }
  ]
}